ziamath/__init__.py
ziamath/__main__.py
ziamath/config.py
ziamath/drawable.py
ziamath/escape_codes.py
ziamath/escapes.py
ziamath/mathfont.py
ziamath/mathtable.py
ziamath/operators.py
ziamath/py.typed
ziamath/styles.py
ziamath/tex.py
ziamath/zmath.py
ziamath/fonts/STIXTwoMath-Regular.ttf
ziamath/fonts/__init__.py
ziamath/nodes/__init__.py
ziamath/nodes/menclose.py
ziamath/nodes/mfenced.py
ziamath/nodes/mfrac.py
ziamath/nodes/mnode.py
ziamath/nodes/mnumber.py
ziamath/nodes/moperator.py
ziamath/nodes/mroot.py
ziamath/nodes/mrow.py
ziamath/nodes/mspace.py
ziamath/nodes/msubsup.py
ziamath/nodes/mtable.py
ziamath/nodes/munderover.py
ziamath/nodes/nodetools.py
ziamath-0.11.dist-info/LICENSE.txt
ziamath-0.11.dist-info/METADATA
ziamath-0.11.dist-info/WHEEL
ziamath-0.11.dist-info/top_level.txt
ziamath-0.11.dist-info/RECORD
